{
    "key": "group_6653e9c50e20f",
    "title": "Block Milestones",
    "fields": [
        {
            "key": "field_6696b1ffec09f",
            "label": "Block Settings",
            "name": "block_settings",
            "aria-label": "",
            "type": "clone",
            "instructions": "",
            "required": 0,
            "conditional_logic": 0,
            "wrapper": {
                "width": "20",
                "class": "",
                "id": ""
            },
            "clone": [
                "group_65f2ed05497f6"
            ],
            "display": "group",
            "layout": "block",
            "prefix_label": 0,
            "prefix_name": 1,
            "acfe_clone_modal": 1,
            "acfe_clone_modal_close": 1,
            "acfe_clone_modal_button": "",
            "acfe_clone_modal_size": "large",
            "acfe_seamless_style": 0
        },
        {
            "key": "field_67118c83bfe8e",
            "label": "Heading",
            "name": "heading",
            "aria-label": "",
            "type": "select",
            "instructions": "",
            "required": 0,
            "conditional_logic": 0,
            "wrapper": {
                "width": "20",
                "class": "acf-heading",
                "id": ""
            },
            "choices": {
                "h1": "h1",
                "h2": "h2",
                "h3": "h3",
                "h4": "h4",
                "h5": "h5",
                "h6": "h6"
            },
            "default_value": "h3",
            "return_format": "value",
            "multiple": 0,
            "allow_null": 0,
            "allow_in_bindings": 0,
            "ui": 0,
            "ajax": 0,
            "placeholder": "",
            "allow_custom": 0,
            "search_placeholder": "",
            "create_options": 0,
            "save_options": 0,
            "pll_default_value": "h3"
        },
        {
            "key": "field_6654042ff071c",
            "label": "Reverse Order",
            "name": "reverse_order",
            "aria-label": "",
            "type": "true_false",
            "instructions": "",
            "required": 0,
            "conditional_logic": 0,
            "wrapper": {
                "width": "20",
                "class": "",
                "id": ""
            },
            "message": "",
            "default_value": 0,
            "ui_on_text": "",
            "ui_off_text": "",
            "ui": 1,
            "pll_default_value": 0
        },
        {
            "key": "field_64e781e91fed9",
            "label": "Timeline",
            "name": "timeline",
            "aria-label": "",
            "type": "repeater",
            "instructions": "",
            "required": 0,
            "conditional_logic": 0,
            "wrapper": {
                "width": "",
                "class": "",
                "id": ""
            },
            "acfe_repeater_stylised_button": 1,
            "layout": "table",
            "pagination": 0,
            "min": 0,
            "max": 0,
            "collapsed": "field_64e781ea1f621",
            "button_label": "Add Item",
            "rows_per_page": 20,
            "sub_fields": [
                {
                    "key": "field_64e781ea1f621",
                    "label": "Title",
                    "name": "title",
                    "aria-label": "",
                    "type": "text",
                    "instructions": "",
                    "required": 0,
                    "conditional_logic": 0,
                    "wrapper": {
                        "width": "30",
                        "class": "",
                        "id": ""
                    },
                    "default_value": "",
                    "maxlength": "",
                    "allow_in_bindings": 1,
                    "placeholder": "",
                    "prepend": "",
                    "append": "",
                    "parent_repeater": "field_64e781e91fed9",
                    "pll_default_value": ""
                },
                {
                    "key": "field_64f7a6c5a0154",
                    "label": "Content",
                    "name": "events",
                    "aria-label": "",
                    "type": "repeater",
                    "instructions": "",
                    "required": 0,
                    "conditional_logic": 0,
                    "wrapper": {
                        "width": "70",
                        "class": "",
                        "id": ""
                    },
                    "acfe_repeater_stylised_button": 1,
                    "layout": "block",
                    "min": 0,
                    "max": 0,
                    "collapsed": "field_64f7a6eaa0155",
                    "button_label": "Add Content",
                    "rows_per_page": 20,
                    "parent_repeater": "field_64e781e91fed9",
                    "sub_fields": [
                        {
                            "key": "field_64f7a6eaa0155",
                            "label": "Description",
                            "name": "description",
                            "aria-label": "",
                            "type": "textarea",
                            "instructions": "",
                            "required": 0,
                            "conditional_logic": 0,
                            "wrapper": {
                                "width": "",
                                "class": "",
                                "id": ""
                            },
                            "default_value": "",
                            "acfe_textarea_code": 0,
                            "maxlength": "",
                            "allow_in_bindings": 1,
                            "rows": "",
                            "placeholder": "",
                            "new_lines": "",
                            "parent_repeater": "field_64f7a6c5a0154",
                            "pll_default_value": ""
                        },
                        {
                            "key": "field_64f7a71fa0156",
                            "label": "Gallery",
                            "name": "gallery",
                            "aria-label": "",
                            "type": "gallery",
                            "instructions": "",
                            "required": 0,
                            "conditional_logic": 0,
                            "wrapper": {
                                "width": "",
                                "class": "",
                                "id": ""
                            },
                            "return_format": "array",
                            "library": "all",
                            "min": "",
                            "max": "",
                            "min_width": "",
                            "min_height": "",
                            "min_size": "",
                            "max_width": "",
                            "max_height": "",
                            "max_size": "",
                            "mime_types": "jpg,jpeg,png,gif,svg,webp,avif",
                            "insert": "append",
                            "preview_size": "thumbnail",
                            "parent_repeater": "field_64f7a6c5a0154"
                        }
                    ]
                }
            ]
        }
    ],
    "location": [
        [
            {
                "param": "block",
                "operator": "==",
                "value": "acf\/milestones"
            }
        ]
    ],
    "menu_order": 0,
    "position": "normal",
    "style": "default",
    "label_placement": "left",
    "instruction_placement": "label",
    "hide_on_screen": "",
    "active": true,
    "description": "",
    "show_in_rest": 0,
    "acfe_display_title": "",
    "acfe_autosync": [
        "json"
    ],
    "acfe_form": 0,
    "acfe_meta": "",
    "acfe_note": "",
    "modified": 1755740603,
    "acfe_categories": {
        "block": "Block"
    }
}